xaal/__init__.py
xaal/htu21d/HTU21D.py
xaal/htu21d/__init__.py
xaal/htu21d/__main__.py
xaal/htu21d/devs.py
xaal/htu21d/i2c_base.py
xaal_htu21d-0.1.2.dist-info/METADATA
xaal_htu21d-0.1.2.dist-info/WHEEL
xaal_htu21d-0.1.2.dist-info/top_level.txt
xaal_htu21d-0.1.2.dist-info/RECORD
